imbue/__init__.py
imbue/abstract.py
imbue/container.py
imbue/contexts/__init__.py
imbue/contexts/abstract.py
imbue/contexts/application.py
imbue/contexts/base.py
imbue/contexts/factory.py
imbue/contexts/task.py
imbue/contexts/thread.py
imbue/dependency.py
imbue/exceptions.py
imbue/fastapi/README.md
imbue/fastapi/__init__.py
imbue/fastapi/app.py
imbue/fastapi/request.py
imbue/package.py
imbue/providers/__init__.py
imbue/providers/abstract.py
imbue/providers/common.py
imbue/providers/function.py
imbue/providers/instance.py
imbue/py.typed
imbue/utils.py
imbue-2.2.1.dist-info/licenses/LICENSE
imbue-2.2.1.dist-info/WHEEL
imbue-2.2.1.dist-info/METADATA
imbue-2.2.1.dist-info/RECORD
