Metadata-Version: 2.4
Name: imbue
Version: 2.2.1
Summary: Type based python dependency injection framework.
Author: Gabriel Pajot
Author-email: Gabriel Pajot <gab@lescactus.eu>
License-Expression: MIT
License-File: LICENSE
Requires-Dist: fastapi>=0.112.1,<2 ; extra == 'fastapi'
Requires-Python: >=3.10
Project-URL: repository, https://github.com/gpajot/imbue
Provides-Extra: fastapi
